AUTHORS.rst
CONTRIBUTORS.md
LICENSE
MANIFEST.in
README.md
requirements.txt
setup.py
tox.ini
climetlab_wekeo_clms/__init__.py
climetlab_wekeo_clms/cgls_continents_wb_v1_1km.py
climetlab_wekeo_clms/cgls_daily10_lst_dc_global_v1.py
climetlab_wekeo_clms/cgls_daily10_lst_dc_global_v2.py
climetlab_wekeo_clms/cgls_daily10_lst_tci_global_v1.py
climetlab_wekeo_clms/cgls_daily10_lst_tci_global_v2.py
climetlab_wekeo_clms/cgls_global_albh_v1_1km.py
climetlab_wekeo_clms/cgls_global_aldh_v1_1km.py
climetlab_wekeo_clms/cgls_global_dmp300_v1_333m.py
climetlab_wekeo_clms/cgls_global_dmp_v2_1km.py
climetlab_wekeo_clms/cgls_global_fapar300_v1_333m.py
climetlab_wekeo_clms/cgls_global_fapar_v1_1km.py
climetlab_wekeo_clms/cgls_global_fapar_v2_1km.py
climetlab_wekeo_clms/cgls_global_fcover300_v1_333m.py
climetlab_wekeo_clms/cgls_global_fcover_v1_1km.py
climetlab_wekeo_clms/cgls_global_fcover_v2_1km.py
climetlab_wekeo_clms/cgls_global_gdmp300_v1_333m.py
climetlab_wekeo_clms/cgls_global_gdmp_v2_1km.py
climetlab_wekeo_clms/cgls_global_lai300_v1_333m.py
climetlab_wekeo_clms/cgls_global_lai_v1_1km.py
climetlab_wekeo_clms/cgls_global_lai_v2_1km.py
climetlab_wekeo_clms/cgls_global_ndvi300_v1_333m.py
climetlab_wekeo_clms/cgls_global_ndvi300_v2_333m.py
climetlab_wekeo_clms/cgls_global_ndvi_st.py
climetlab_wekeo_clms/cgls_global_ndvi_v2_1km.py
climetlab_wekeo_clms/cgls_global_ndvi_v2_1km_lts.py
climetlab_wekeo_clms/cgls_global_ndvi_v3_1km.py
climetlab_wekeo_clms/cgls_global_swi10_v3_0_1degree.py
climetlab_wekeo_clms/cgls_global_swi_static_v1_0_1degree.py
climetlab_wekeo_clms/cgls_global_wb300_v1_333m.py
climetlab_wekeo_clms/cgls_hourly_lst_global_v1.py
climetlab_wekeo_clms/cgls_hourly_lst_global_v2.py
climetlab_wekeo_clms/main.py
climetlab_wekeo_clms/version
climetlab_wekeo_clms.egg-info/PKG-INFO
climetlab_wekeo_clms.egg-info/SOURCES.txt
climetlab_wekeo_clms.egg-info/dependency_links.txt
climetlab_wekeo_clms.egg-info/entry_points.txt
climetlab_wekeo_clms.egg-info/requires.txt
climetlab_wekeo_clms.egg-info/top_level.txt
climetlab_wekeo_clms.egg-info/zip-safe
docs/Makefile
docs/make.bat
docs/images/lst-line-comparison.png
docs/images/lst-line-plot.png
docs/images/plot.png
docs/images/wekeo-viewer.png
docs/source/changelog.rst
docs/source/conf.py
docs/source/index.rst
docs/source/installation.rst
